[
	{
		"_id": "7dc2468e-d1ea-43d8-b316-87d3bf4a1faa",
		"type": "Period",
		"employee_id": "4bfce846-8550-43b2-b387-27691d2199ff",
		"startDate": "2017-01-01T00:00",
		"endDate": "2017-12-31T00:00",
		"status": "Goals - Complete",
		"goals": [
			{
				"id": "8791578b-d679-4844-a45a-60b88e34960b",
				"section_id": "d9c8bb3d-087b-423d-9122-d4178b3e49de",						
				"title": "Lead and contribute to the development of EBS 3.4",
				"measurement": "Work with the development team to ensure all tasks are completed successfully. Assist the development team with technical issues as needed. Complete all assigned tasks a resolve assigned bugs. Ensure that the project will meet all milestones defined by the customer towards the successful development of EBS 3.4.",
				"dueDate": "2017-12-31T00:00",
				"status": "In Progress",
				"achievements": []
			},
			{
				"id": "e45549c7-2c6b-4b2b-9a00-ec97c2d398f4",
				"section_id": "d9c8bb3d-087b-423d-9122-d4178b3e49de",						
				"title": "Contribute to the successful maintenance of EBS",
				"measurement": "Complete assigned tasks to ensure that enhancements to the EBS suite are successfully deployed every 3 months.",
				"dueDate": "2017-12-31T00:00",
				"status": "Not Started",
				"achievements": []
			},
			{
				"id": "ade39a0b-158e-467d-a445-dacdbffc7d44",
				"section_id": "d9c8bb3d-087b-423d-9122-d4178b3e49de",						
				"title": "Migrate Development from LDRNET to C2S",
				"measurement": "Contribute to the successful migration of the development environment from LDRNET to C2S as requested by the customer.",
				"dueDate": "2017-12-31T00:00",
				"status": "In Progress",
				"achievements": [
					{
						"id": "a31b2c18-cf6d-4530-a54f-c84c869eae31",
						"createdDate": "2017-06-13T00:00",
						"startDate": "2017-05-29T00:00",
						"endDate": "2017-05-29T00:00",
						"description": "Configure Developer workstation with Roles and Features, SQL Server 2014, Visual Studio 2015, MS Office 2010. Verify ability to compile and execute code against DEV-DB01 and local databases."
					},
					{
						"id": "41852d55-6441-43fc-b7ef-545c8e30a00d",
						"createdDate": "2017-06-13T00:00",
						"startDate": "2017-06-01T00:00",
						"endDate": "2017-06-01T00:00",
						"description": "Configure QA workstation with SQL Server Management Studio and MS Office 2010. Verify ability to connect from SSMS to DEV-DB01 server. Verify ability to browse to EBS applications."
					},
					{
						"id": "d125e95d-2576-4e41-b7d7-770a31c509ec",
						"createdDate": "2017-06-13T00:00",
						"startDate": "2017-06-08T00:00",
						"endDate": "2017-06-08T00:00",
						"description": "Configure TFS servers in C2S with Roles and Features.  Install SQL Server 2014 on TFS database server."
					},
					{
						"id": "944cf8a5-dc9d-4f5c-a1a8-c6d8604b8ce7",
						"createdDate": "2017-06-13T00:00",
						"startDate": "2017-06-08T00:00",
						"endDate": "2017-06-08T00:00",
						"description": "Configure TFS servers with Roles and Features, Windows patches, SQL Server 2014 and TFS 2015. Restore the BAMOM and BPO TFS databases."
					},
					{
						"id": "5eb1486b-4c2f-4008-a9d2-1d6b811aee14",
						"createdDate": "2017-06-13T00:00",
						"startDate": "2017-06-09T00:00",
						"endDate": "2017-06-09T00:00",
						"description": "Verify the configuration of \"Developer Workstation 2\" and confirm that SQL Server 2014 is working when a server is created from an AMI."
					}
				]
			},
			{
				"id": "1d10f7de-2ea3-44b2-84ac-378a4c108ab4",
				"section_id": "d9c8bb3d-087b-423d-9122-d4178b3e49de",						
				"title": "Provide Tier 3 support for the EBS suite",
				"measurement": "Provide support for production issues and successfully implement solutions to ensure customer satisfaction.",
				"dueDate": "2017-12-31T00:00",
				"status": "In Progress",
				"achievements": [
					{
						"id": "da6f71c5-7703-4b9c-af14-460b2508779c",
						"createdDate": "2017-06-08T00:00",
						"startDate": "2017-04-26T00:00",
						"endDate": "2017-04-26T00:00",
						"description": "NETS ticket number SD1347641 - Update Help OCA script that is used to delete inventory schedules."
					},
					{
						"id": "2824ca79-4945-4697-8f46-67dd91484af5",
						"createdDate": "2017-06-08T00:00",
						"startDate": "2017-05-10T00:00",
						"endDate": "2017-05-10T00:00",
						"description": "BOSS ticket number IM48815 - Write a script to fix LDDT submission counts in Focus LDDT list."
					},
					{
						"id": "74b43a02-8617-480b-90ea-6d62a2ca718a",
						"createdDate": "2017-06-08T00:00",
						"startDate": "2017-05-10T00:00",
						"endDate": "2017-05-10T00:00",
						"description": "BOSS ticket numbers IM49727, IM49444, IM49642 - Modify the Disposal stored procedure to move property in the inventory submission from disposal cases where the property has been withdrawn over to the submitted inventory schedule."
					},
					{
						"id": "ab3c4935-cf4e-4f1a-aa22-82b2ccb23591",
						"createdDate": "2017-06-08T00:00",
						"startDate": "2017-05-10T00:00",
						"endDate": "2017-05-10T00:00",
						"description": "BOSS ticket numbers IM49443, IM49746 - Fix the calculation of current quantity and acquisition cost when submitting a material inventory schedule."
					},
					{
						"id": "432b9745-9aab-4079-a89c-dd1adc1a911f",
						"createdDate": "2017-06-08T00:00",
						"startDate": "2017-05-10T00:00",
						"endDate": "2017-05-10T00:00",
						"description": "BOSS ticket number IM48742 - Display the contract number in a draft invoice PDF document when generated from Focus."
					},
					{
						"id": "da47f52f-fc8e-4d9b-8f17-dfa813238002",
						"createdDate": "2017-06-08T00:00",
						"startDate": "2017-05-10T00:00",
						"endDate": "2017-05-10T00:00",
						"description": "BOSS ticket numbers IM48980, IM49432, IM49462, IM49681, IM49659 - Fix the validation of invoice attachment file extensions to be case insensitive."
					},

					{
						"id": "3a4f4217-f33c-418a-a4c9-85469ffc4072",
						"createdDate": "2017-06-08T00:00",
						"startDate": "2017-06-08T00:00",
						"endDate": "2017-06-08T00:00",
						"description": "BOSS ticket number  - Fix script errors in Focus so that it will render properly when a user does not have permissions to the application."
					},

					{
						"id": "0093b791-491f-415d-aaae-a477310bb41c",
						"createdDate": "2017-06-08T00:00",
						"startDate": "2017-06-08T00:00",
						"endDate": "2017-06-08T00:00",
						"description": "BOSS ticket number  - Write a script to fix Negative Line Item Submissions where the contract does not have active inventory."
					}
				]
			}
		]
	},
	{
		"_id": "835ec0ed-2401-45e5-95ee-443dbe7224ef",
		"type": "Period",
		"employee_id": "4bfce846-8550-43b2-b387-27691d2199ff",
		"startDate": "2016-01-01T00:00",
		"endDate": "2016-12-31T00:00",
		"status": "Mgr Eval - In Progress",
		"goals": [
			{
				"id": "29f17dd5-7131-4c5d-abb8-dcf177445797",
				"section_id": "d9c8bb3d-087b-423d-9122-d4178b3e49de",
				"title": "Development lead for EBS 3.4 Development",
				"measurement": "The customer priority changed from the development of EBS 3.4 to applying software currency to EBS 3.3 and then another change in priority to applying software currency to EBS 3.2.",
				"dueDate": "2017-03-31T00:00",
				"status": "In Progress",
				"employeeComments": "I have been leading the team in the upgrade of 3rd party libraries to EBS 3.3 and then to EBS 3.2.  I have handled the merging of code between the different branches of code within TFS.  The software currency changes have been verified and the team is prepared to deploy the software currency changes on December 16th.",
				"supervisorComments": "",
				"achievements": []
			}
		]
	}
]
